{
  "Searching": {
    "description": "",
    "duration": 248,
    "genre": "Robin",
    "title": "When The World Turns Grey",
    "username": "Robin Schulz",
    "artist": "Princess Chelsea",
    "remixArtist": null,
    "labelname": "",
    "id": 76374542,
    "isRemix": false,
    "search_stage": 3,
    "url": "https://soundcloud.com/robin-schulz/princess-chelsea-when-the-world-turns-grey-robin-schulz-heyhey-bootleg-1"
  },
  "Results": [
    {
      "description": "",
      "duration": 260,
      "genre": "",
      "title": "Cigarette Duet",
      "username": "Princess Chelsea",
      "artist": "Princess Chelsea",
      "remixArtist": null,
      "labelname": "",
      "id": 140551809,
      "isRemix": false,
      "search_stage": 0,
      "url": "https://www.deezer.com/track/140551809"
    },
    {
      "description": "",
      "duration": 258,
      "genre": "",
      "title": "Yulia",
      "username": "Princess Chelsea",
      "artist": "Princess Chelsea",
      "remixArtist": null,
      "labelname": "",
      "id": 140553031,
      "isRemix": false,
      "search_stage": 0,
      "url": "https://www.deezer.com/track/140553031"
    },
    {
      "description": "",
      "duration": 260,
      "genre": "",
      "title": "Cigarette Duet",
      "username": "Princess Chelsea",
      "artist": "Princess Chelsea",
      "remixArtist": null,
      "labelname": "",
      "id": 140553039,
      "isRemix": false,
      "search_stage": 0,
      "url": "https://www.deezer.com/track/140553039"
    },
    {
      "description": "",
      "duration": 229,
      "genre": "",
      "title": "Come as You Are",
      "username": "Princess Chelsea",
      "artist": "Princess Chelsea",
      "remixArtist": null,
      "labelname": "",
      "id": 133178590,
      "isRemix": false,
      "search_stage": 0,
      "url": "https://www.deezer.com/track/133178590"
    },
    {
      "description": "",
      "duration": 246,
      "genre": "",
      "title": "I Love My Boyfriend",
      "username": "Princess Chelsea",
      "artist": "Princess Chelsea",
      "remixArtist": null,
      "labelname": "",
      "id": 504019582,
      "isRemix": false,
      "search_stage": 0,
      "url": "https://www.deezer.com/track/504019582"
    },
    {
      "description": "",
      "duration": 204,
      "genre": "",
      "title": "Monkey Eats Bananas",
      "username": "Princess Chelsea",
      "artist": "Princess Chelsea",
      "remixArtist": null,
      "labelname": "",
      "id": 140553035,
      "isRemix": false,
      "search_stage": 0,
      "url": "https://www.deezer.com/track/140553035"
    },
    {
      "description": "",
      "duration": 181,
      "genre": "",
      "title": "Wasting Time",
      "username": "Princess Chelsea",
      "artist": "Princess Chelsea",
      "remixArtist": null,
      "labelname": "",
      "id": 504019592,
      "isRemix": false,
      "search_stage": 0,
      "url": "https://www.deezer.com/track/504019592"
    },
    {
      "description": "",
      "duration": 254,
      "genre": "",
      "title": "When the World Turns Grey",
      "username": "Princess Chelsea",
      "artist": "Princess Chelsea",
      "remixArtist": null,
      "labelname": "",
      "id": 388079881,
      "isRemix": false,
      "search_stage": 0,
      "url": "https://www.deezer.com/track/388079881"
    },
    {
      "description": "",
      "duration": 232,
      "genre": "",
      "title": "World Turns Grey",
      "username": "Robin Schulz",
      "artist": "Robin Schulz",
      "remixArtist": null,
      "labelname": "",
      "id": 107471440,
      "isRemix": false,
      "search_stage": 0,
      "url": "https://www.deezer.com/track/107471440"
    },
    {
      "description": "",
      "duration": 207,
      "genre": "",
      "title": "Caution Repetitive",
      "username": "Princess Chelsea",
      "artist": "Princess Chelsea",
      "remixArtist": null,
      "labelname": "",
      "id": 140553037,
      "isRemix": false,
      "search_stage": 0,
      "url": "https://www.deezer.com/track/140553037"
    },
    {
      "description": "",
      "duration": 126,
      "genre": "",
      "title": "Positive Guy Meets Negative Man",
      "username": "Princess Chelsea",
      "artist": "Princess Chelsea",
      "remixArtist": null,
      "labelname": "",
      "id": 140551811,
      "isRemix": false,
      "search_stage": 0,
      "url": "https://www.deezer.com/track/140551811"
    },
    {
      "description": "",
      "duration": 233,
      "genre": "",
      "title": "Morning Sun",
      "username": "Princess Chelsea",
      "artist": "Princess Chelsea",
      "remixArtist": null,
      "labelname": "",
      "id": 132702956,
      "isRemix": false,
      "search_stage": 0,
      "url": "https://www.deezer.com/track/132702956"
    },
    {
      "description": "",
      "duration": 149,
      "genre": "",
      "title": "Ice Reign",
      "username": "Princess Chelsea",
      "artist": "Princess Chelsea",
      "remixArtist": null,
      "labelname": "",
      "id": 140553033,
      "isRemix": false,
      "search_stage": 0,
      "url": "https://www.deezer.com/track/140553033"
    },
    {
      "description": "",
      "duration": 197,
      "genre": "",
      "title": "Machines of Loving Grace",
      "username": "Princess Chelsea",
      "artist": "Princess Chelsea",
      "remixArtist": null,
      "labelname": "",
      "id": 140553029,
      "isRemix": false,
      "search_stage": 0,
      "url": "https://www.deezer.com/track/140553029"
    },
    {
      "description": "",
      "duration": 293,
      "genre": "",
      "title": "Frack",
      "username": "Princess Chelsea",
      "artist": "Princess Chelsea",
      "remixArtist": null,
      "labelname": "",
      "id": 140553045,
      "isRemix": false,
      "search_stage": 0,
      "url": "https://www.deezer.com/track/140553045"
    },
    {
      "description": "",
      "duration": 223,
      "genre": "",
      "title": "Ice Reign",
      "username": "Princess Chelsea",
      "artist": "Princess Chelsea",
      "remixArtist": null,
      "labelname": "",
      "id": 140553049,
      "isRemix": false,
      "search_stage": 0,
      "url": "https://www.deezer.com/track/140553049"
    },
    {
      "description": "",
      "duration": 165,
      "genre": "",
      "title": "Too Fast to Live",
      "username": "Princess Chelsea",
      "artist": "Princess Chelsea",
      "remixArtist": null,
      "labelname": "",
      "id": 140553041,
      "isRemix": false,
      "search_stage": 0,
      "url": "https://www.deezer.com/track/140553041"
    },
    {
      "description": "",
      "duration": 187,
      "genre": "",
      "title": "Overseas",
      "username": "Princess Chelsea",
      "artist": "Princess Chelsea",
      "remixArtist": null,
      "labelname": "",
      "id": 140553043,
      "isRemix": false,
      "search_stage": 0,
      "url": "https://www.deezer.com/track/140553043"
    },
    {
      "description": "",
      "duration": 253,
      "genre": "",
      "title": "When the World Turns Grey",
      "username": "Princess Chelsea",
      "artist": "Princess Chelsea",
      "remixArtist": null,
      "labelname": "",
      "id": 140520215,
      "isRemix": false,
      "search_stage": 0,
      "url": "https://www.deezer.com/track/140520215"
    },
    {
      "description": "",
      "duration": 360,
      "genre": "",
      "title": "Goodnight Little Robot Child",
      "username": "Princess Chelsea",
      "artist": "Princess Chelsea",
      "remixArtist": null,
      "labelname": "",
      "id": 140553047,
      "isRemix": false,
      "search_stage": 0,
      "url": "https://www.deezer.com/track/140553047"
    },
    {
      "description": "",
      "duration": 302,
      "genre": "",
      "title": "Too Many People",
      "username": "Princess Chelsea",
      "artist": "Princess Chelsea",
      "remixArtist": null,
      "labelname": "",
      "id": 388079911,
      "isRemix": false,
      "search_stage": 0,
      "url": "https://www.deezer.com/track/388079911"
    },
    {
      "description": "",
      "duration": 245,
      "genre": "",
      "title": "Is It All OK?",
      "username": "Princess Chelsea",
      "artist": "Princess Chelsea",
      "remixArtist": null,
      "labelname": "",
      "id": 388079891,
      "isRemix": false,
      "search_stage": 0,
      "url": "https://www.deezer.com/track/388079891"
    },
    {
      "description": "",
      "duration": 298,
      "genre": "",
      "title": "No Church on Sunday",
      "username": "Princess Chelsea",
      "artist": "Princess Chelsea",
      "remixArtist": null,
      "labelname": "",
      "id": 388079901,
      "isRemix": false,
      "search_stage": 0,
      "url": "https://www.deezer.com/track/388079901"
    },
    {
      "description": "",
      "duration": 296,
      "genre": "",
      "title": "We Are Very Happy",
      "username": "Princess Chelsea",
      "artist": "Princess Chelsea",
      "remixArtist": null,
      "labelname": "",
      "id": 388079921,
      "isRemix": false,
      "search_stage": 0,
      "url": "https://www.deezer.com/track/388079921"
    },
    {
      "description": "",
      "duration": 234,
      "genre": "",
      "title": "The Loneliest Girl",
      "username": "Princess Chelsea",
      "artist": "Princess Chelsea",
      "remixArtist": null,
      "labelname": "",
      "id": 504019602,
      "isRemix": false,
      "search_stage": 0,
      "url": "https://www.deezer.com/track/504019602"
    }
  ]
}