{
  "Searching": {
    "description": "",
    "duration": 236,
    "genre": "DVBBS",
    "title": "TSUNAMI",
    "username": "DVBBS",
    "artist": "DVBBS  Borgeous",
    "remixArtist": null,
    "labelname": "",
    "id": 46710332,
    "isRemix": false,
    "search_stage": 3,
    "url": "https://soundcloud.com/dvbbs/dvbbs-borgeous-tsunami"
  },
  "Results": [
    {
      "description": "",
      "duration": 236,
      "genre": "",
      "title": "Tsunami",
      "username": "DVBBS",
      "artist": "DVBBS",
      "remixArtist": null,
      "labelname": "",
      "id": 463375512,
      "isRemix": false,
      "search_stage": 0,
      "url": "https://www.deezer.com/track/463375512"
    },
    {
      "description": "",
      "duration": 159,
      "genre": "",
      "title": "Tsunami",
      "username": "DVBBS",
      "artist": "DVBBS",
      "remixArtist": null,
      "labelname": "",
      "id": 76411968,
      "isRemix": false,
      "search_stage": 0,
      "url": "https://www.deezer.com/track/76411968"
    },
    {
      "description": "",
      "duration": 159,
      "genre": "",
      "title": "Tsunami",
      "username": "DVBBS",
      "artist": "DVBBS",
      "remixArtist": null,
      "labelname": "",
      "id": 77930911,
      "isRemix": false,
      "search_stage": 0,
      "url": "https://www.deezer.com/track/77930911"
    },
    {
      "description": "",
      "duration": 159,
      "genre": "",
      "title": "Tsunami",
      "username": "DVBBS",
      "artist": "DVBBS",
      "remixArtist": null,
      "labelname": "",
      "id": 481411292,
      "isRemix": false,
      "search_stage": 0,
      "url": "https://www.deezer.com/track/481411292"
    },
    {
      "description": "",
      "duration": 143,
      "genre": "",
      "title": "Tsunami",
      "username": "Sevan",
      "artist": "Sevan",
      "remixArtist": null,
      "labelname": "",
      "id": 72109047,
      "isRemix": false,
      "search_stage": 0,
      "url": "https://www.deezer.com/track/72109047"
    },
    {
      "description": "",
      "duration": 143,
      "genre": "",
      "title": "Tsunami",
      "username": "Hadon Sky",
      "artist": "Hadon Sky",
      "remixArtist": null,
      "labelname": "",
      "id": 72417531,
      "isRemix": false,
      "search_stage": 0,
      "url": "https://www.deezer.com/track/72417531"
    },
    {
      "description": "",
      "duration": 144,
      "genre": "",
      "title": "Tsunami",
      "username": "Sevan",
      "artist": "Sevan",
      "remixArtist": null,
      "labelname": "",
      "id": 72107030,
      "isRemix": false,
      "search_stage": 0,
      "url": "https://www.deezer.com/track/72107030"
    },
    {
      "description": "",
      "duration": 143,
      "genre": "",
      "title": "Tsunami",
      "username": "Sevan",
      "artist": "Sevan",
      "remixArtist": null,
      "labelname": "",
      "id": 72183512,
      "isRemix": false,
      "search_stage": 0,
      "url": "https://www.deezer.com/track/72183512"
    },
    {
      "description": "",
      "duration": 247,
      "genre": "",
      "title": "Hey Brother",
      "username": "Henri Pfr",
      "artist": "Henri Pfr",
      "remixArtist": null,
      "labelname": "",
      "id": 72183514,
      "isRemix": false,
      "search_stage": 0,
      "url": "https://www.deezer.com/track/72183514"
    },
    {
      "description": "",
      "duration": 337,
      "genre": "",
      "title": "Tsunami",
      "username": "DVBBS",
      "artist": "DVBBS",
      "remixArtist": "Blasterjaxx",
      "labelname": "",
      "id": 470425092,
      "isRemix": true,
      "search_stage": 0,
      "url": "https://www.deezer.com/track/470425092"
    },
    {
      "description": "",
      "duration": 159,
      "genre": "",
      "title": "Tsunami",
      "username": "Chart Hitz",
      "artist": "Chart Hitz",
      "remixArtist": null,
      "labelname": "",
      "id": 75118317,
      "isRemix": false,
      "search_stage": 0,
      "url": "https://www.deezer.com/track/75118317"
    },
    {
      "description": "",
      "duration": 159,
      "genre": "",
      "title": "Tsunami",
      "username": "This Is Popstarz",
      "artist": "This Is Popstarz",
      "remixArtist": null,
      "labelname": "",
      "id": 75118293,
      "isRemix": false,
      "search_stage": 0,
      "url": "https://www.deezer.com/track/75118293"
    },
    {
      "description": "",
      "duration": 213,
      "genre": "",
      "title": "Wrecking Ball",
      "username": "Lin J",
      "artist": "Lin J",
      "remixArtist": null,
      "labelname": "",
      "id": 72109050,
      "isRemix": false,
      "search_stage": 0,
      "url": "https://www.deezer.com/track/72109050"
    },
    {
      "description": "",
      "duration": 217,
      "genre": "",
      "title": "Get Lucky",
      "username": "Jim Eyes",
      "artist": "Jim Eyes",
      "remixArtist": null,
      "labelname": "",
      "id": 72109054,
      "isRemix": false,
      "search_stage": 0,
      "url": "https://www.deezer.com/track/72109054"
    },
    {
      "description": "",
      "duration": 148,
      "genre": "",
      "title": "La La La",
      "username": "Tom Harris",
      "artist": "Tom Harris",
      "remixArtist": null,
      "labelname": "",
      "id": 72109057,
      "isRemix": false,
      "search_stage": 0,
      "url": "https://www.deezer.com/track/72109057"
    },
    {
      "description": "",
      "duration": 221,
      "genre": "",
      "title": "Hold On, We're Going Home",
      "username": "Walby Say",
      "artist": "Walby Say",
      "remixArtist": null,
      "labelname": "",
      "id": 72109053,
      "isRemix": false,
      "search_stage": 0,
      "url": "https://www.deezer.com/track/72109053"
    },
    {
      "description": "",
      "duration": 143,
      "genre": "",
      "title": "Tsunami",
      "username": "Sevan",
      "artist": "Sevan",
      "remixArtist": null,
      "labelname": "",
      "id": 72380453,
      "isRemix": false,
      "search_stage": 0,
      "url": "https://www.deezer.com/track/72380453"
    },
    {
      "description": "",
      "duration": 215,
      "genre": "",
      "title": "Wrecking Ball",
      "username": "Lin J",
      "artist": "Lin J",
      "remixArtist": null,
      "labelname": "",
      "id": 72109049,
      "isRemix": false,
      "search_stage": 0,
      "url": "https://www.deezer.com/track/72109049"
    },
    {
      "description": "",
      "duration": 242,
      "genre": "",
      "title": "Sonnentanz",
      "username": "Ray J",
      "artist": "Ray J",
      "remixArtist": null,
      "labelname": "",
      "id": 72380470,
      "isRemix": false,
      "search_stage": 0,
      "url": "https://www.deezer.com/track/72380470"
    },
    {
      "description": "",
      "duration": 144,
      "genre": "",
      "title": "Tsunami",
      "username": "Sevan",
      "artist": "Sevan",
      "remixArtist": null,
      "labelname": "",
      "id": 72107032,
      "isRemix": true,
      "search_stage": 0,
      "url": "https://www.deezer.com/track/72107032"
    },
    {
      "description": "",
      "duration": 148,
      "genre": "",
      "title": "La La La",
      "username": "Tom Harris",
      "artist": "Tom Harris",
      "remixArtist": null,
      "labelname": "",
      "id": 72109058,
      "isRemix": false,
      "search_stage": 0,
      "url": "https://www.deezer.com/track/72109058"
    },
    {
      "description": "",
      "duration": 170,
      "genre": "",
      "title": "Talk Dirty",
      "username": "Walby Say",
      "artist": "Walby Say",
      "remixArtist": null,
      "labelname": "",
      "id": 72109051,
      "isRemix": false,
      "search_stage": 0,
      "url": "https://www.deezer.com/track/72109051"
    },
    {
      "description": "",
      "duration": 144,
      "genre": "",
      "title": "Tsunami",
      "username": "DJ Danerston",
      "artist": "DJ Danerston",
      "remixArtist": null,
      "labelname": "",
      "id": 125753246,
      "isRemix": false,
      "search_stage": 0,
      "url": "https://www.deezer.com/track/125753246"
    },
    {
      "description": "",
      "duration": 148,
      "genre": "",
      "title": "La La La",
      "username": "Tom Harris",
      "artist": "Tom Harris",
      "remixArtist": null,
      "labelname": "",
      "id": 72109059,
      "isRemix": false,
      "search_stage": 0,
      "url": "https://www.deezer.com/track/72109059"
    },
    {
      "description": "",
      "duration": 150,
      "genre": "",
      "title": "Get Lucky",
      "username": "Jim Eyes",
      "artist": "Jim Eyes",
      "remixArtist": null,
      "labelname": "",
      "id": 72109055,
      "isRemix": false,
      "search_stage": 0,
      "url": "https://www.deezer.com/track/72109055"
    }
  ]
}