{
  "Searching": {
    "description": "'@Apster - Get Down Like That' is now available on all portals. Buy/stream it here: wallrecordings.lnk.to/getdownlikethat\n\nFollow Wall Recordings\nYouTube: bit.ly/WallRecordingsTV\nFacebook: www.facebook.com/WallRecordings\nTwitter: twitter.com/wallrecordings\n\nFollow Apster\nwww.facebook.com/apsterofficial\nwww.twitter.com/DJApster\nwww.instagram.com/djapster",
    "duration": 174,
    "genre": "Wall Recordings",
    "title": "Get Down Like That",
    "username": "Wall Recordings",
    "artist": "Apster",
    "remixArtist": null,
    "labelname": "",
    "id": 46710332,
    "isRemix": false,
    "search_stage": 3,
    "url": "https://soundcloud.com/wall-recordings/apster-get-down-like-that-out-now"
  },
  "Results": [
    {
      "description": "",
      "duration": 195,
      "genre": "",
      "title": "No Style",
      "username": "Bassjackers",
      "artist": "Bassjackers",
      "remixArtist": null,
      "labelname": "",
      "id": 630207152,
      "isRemix": false,
      "search_stage": 0,
      "url": "https://www.deezer.com/track/630207152"
    },
    {
      "description": "",
      "duration": 211,
      "genre": "",
      "title": "Believe",
      "username": "Apster",
      "artist": "Apster",
      "remixArtist": null,
      "labelname": "",
      "id": 662351682,
      "isRemix": false,
      "search_stage": 0,
      "url": "https://www.deezer.com/track/662351682"
    },
    {
      "description": "",
      "duration": 171,
      "genre": "",
      "title": "Get It In",
      "username": "Apster",
      "artist": "Apster",
      "remixArtist": null,
      "labelname": "",
      "id": 130117023,
      "isRemix": false,
      "search_stage": 0,
      "url": "https://www.deezer.com/track/130117023"
    },
    {
      "description": "",
      "duration": 281,
      "genre": "",
      "title": "Blackbox",
      "username": "Apster",
      "artist": "Apster",
      "remixArtist": null,
      "labelname": "",
      "id": 461387262,
      "isRemix": false,
      "search_stage": 0,
      "url": "https://www.deezer.com/track/461387262"
    },
    {
      "description": "",
      "duration": 191,
      "genre": "",
      "title": "Drop That",
      "username": "Afrojack",
      "artist": "Afrojack",
      "remixArtist": null,
      "labelname": "",
      "id": 127803317,
      "isRemix": false,
      "search_stage": 0,
      "url": "https://www.deezer.com/track/127803317"
    },
    {
      "description": "",
      "duration": 191,
      "genre": "",
      "title": "Ghostchild",
      "username": "Firebeatz",
      "artist": "Firebeatz",
      "remixArtist": null,
      "labelname": "",
      "id": 461015002,
      "isRemix": false,
      "search_stage": 0,
      "url": "https://www.deezer.com/track/461015002"
    },
    {
      "description": "",
      "duration": 249,
      "genre": "",
      "title": "Get Down Like That",
      "username": "Apster",
      "artist": "Apster",
      "remixArtist": null,
      "labelname": "",
      "id": 452704012,
      "isRemix": false,
      "search_stage": 0,
      "url": "https://www.deezer.com/track/452704012"
    },
    {
      "description": "",
      "duration": 272,
      "genre": "",
      "title": "Soundboy",
      "username": "Apster",
      "artist": "Apster",
      "remixArtist": null,
      "labelname": "",
      "id": 470699242,
      "isRemix": false,
      "search_stage": 0,
      "url": "https://www.deezer.com/track/470699242"
    },
    {
      "description": "",
      "duration": 152,
      "genre": "",
      "title": "Soundboy",
      "username": "Apster",
      "artist": "Apster",
      "remixArtist": null,
      "labelname": "",
      "id": 466017772,
      "isRemix": false,
      "search_stage": 0,
      "url": "https://www.deezer.com/track/466017772"
    },
    {
      "description": "",
      "duration": 158,
      "genre": "",
      "title": "Stick Up",
      "username": "La Fuente",
      "artist": "La Fuente",
      "remixArtist": null,
      "labelname": "",
      "id": 128467529,
      "isRemix": false,
      "search_stage": 0,
      "url": "https://www.deezer.com/track/128467529"
    },
    {
      "description": "",
      "duration": 303,
      "genre": "",
      "title": "Klambu",
      "username": "Bassjackers  Apster",
      "artist": "Bassjackers & Apster",
      "remixArtist": null,
      "labelname": "",
      "id": 64965709,
      "isRemix": false,
      "search_stage": 0,
      "url": "https://www.deezer.com/track/64965709"
    },
    {
      "description": "",
      "duration": 297,
      "genre": "",
      "title": "Photobomb",
      "username": "Apster",
      "artist": "Apster",
      "remixArtist": null,
      "labelname": "",
      "id": 462122222,
      "isRemix": false,
      "search_stage": 0,
      "url": "https://www.deezer.com/track/462122222"
    },
    {
      "description": "",
      "duration": 219,
      "genre": "",
      "title": "The Story",
      "username": "Apster",
      "artist": "Apster",
      "remixArtist": null,
      "labelname": "",
      "id": 132478864,
      "isRemix": false,
      "search_stage": 0,
      "url": "https://www.deezer.com/track/132478864"
    },
    {
      "description": "",
      "duration": 241,
      "genre": "",
      "title": "Alcohol",
      "username": "Apster",
      "artist": "Apster",
      "remixArtist": null,
      "labelname": "",
      "id": 635684302,
      "isRemix": false,
      "search_stage": 0,
      "url": "https://www.deezer.com/track/635684302"
    },
    {
      "description": "",
      "duration": 109,
      "genre": "",
      "title": "Let's Get Wild",
      "username": "Firebeatz",
      "artist": "Firebeatz",
      "remixArtist": null,
      "labelname": "",
      "id": 407429332,
      "isRemix": false,
      "search_stage": 0,
      "url": "https://www.deezer.com/track/407429332"
    },
    {
      "description": "",
      "duration": 281,
      "genre": "",
      "title": "Ghostchild",
      "username": "Firebeatz",
      "artist": "Firebeatz",
      "remixArtist": null,
      "labelname": "",
      "id": 461388402,
      "isRemix": false,
      "search_stage": 0,
      "url": "https://www.deezer.com/track/461388402"
    },
    {
      "description": "",
      "duration": 181,
      "genre": "",
      "title": "Get Down Like That",
      "username": "Apster",
      "artist": "Apster",
      "remixArtist": null,
      "labelname": "",
      "id": 452704022,
      "isRemix": false,
      "search_stage": 0,
      "url": "https://www.deezer.com/track/452704022"
    },
    {
      "description": "",
      "duration": 332,
      "genre": "",
      "title": "Threat To Our Existence",
      "username": "Activator",
      "artist": "Activator",
      "remixArtist": null,
      "labelname": "",
      "id": 35793291,
      "isRemix": false,
      "search_stage": 0,
      "url": "https://www.deezer.com/track/35793291"
    },
    {
      "description": "",
      "duration": 152,
      "genre": "",
      "title": "Stick Up",
      "username": "La Fuente",
      "artist": "La Fuente",
      "remixArtist": null,
      "labelname": "",
      "id": 136927490,
      "isRemix": false,
      "search_stage": 0,
      "url": "https://www.deezer.com/track/136927490"
    },
    {
      "description": "",
      "duration": 305,
      "genre": "",
      "title": "Bombazi",
      "username": "JoeySuki  Apster",
      "artist": "JoeySuki & Apster",
      "remixArtist": null,
      "labelname": "",
      "id": 64965707,
      "isRemix": false,
      "search_stage": 0,
      "url": "https://www.deezer.com/track/64965707"
    },
    {
      "description": "",
      "duration": 322,
      "genre": "",
      "title": "Bucklekneez",
      "username": "Apster",
      "artist": "Apster",
      "remixArtist": null,
      "labelname": "",
      "id": 461945162,
      "isRemix": false,
      "search_stage": 0,
      "url": "https://www.deezer.com/track/461945162"
    },
    {
      "description": "",
      "duration": 311,
      "genre": "",
      "title": "Told Ya",
      "username": "Sandro Silva",
      "artist": "Sandro Silva",
      "remixArtist": "Apster",
      "labelname": "",
      "id": 803441302,
      "isRemix": true,
      "search_stage": 0,
      "url": "https://www.deezer.com/track/803441302"
    },
    {
      "description": "",
      "duration": 297,
      "genre": "",
      "title": "16",
      "username": "Jorn",
      "artist": "Jorn",
      "remixArtist": "Apster",
      "labelname": "",
      "id": 10915805,
      "isRemix": true,
      "search_stage": 0,
      "url": "https://www.deezer.com/track/10915805"
    },
    {
      "description": "",
      "duration": 332,
      "genre": "",
      "title": "Threat to Our Existence",
      "username": "Activator",
      "artist": "Activator",
      "remixArtist": null,
      "labelname": "",
      "id": 10118355,
      "isRemix": false,
      "search_stage": 0,
      "url": "https://www.deezer.com/track/10118355"
    },
    {
      "description": "",
      "duration": 307,
      "genre": "",
      "title": "When I Dip",
      "username": "Bingo Players",
      "artist": "Bingo Players",
      "remixArtist": "Apster",
      "labelname": "",
      "id": 64729477,
      "isRemix": true,
      "search_stage": 0,
      "url": "https://www.deezer.com/track/64729477"
    }
  ]
}