{
  "Searching": {
    "description": "Crywolf\nhttps://soundcloud.com/crywolf\nhttps://www.facebook.com/RunCryWolf\nhttps://twitter.com/RunCryWolf\n\nSkrux\nhttps://soundcloud.com/skrux\nhttps://www.facebook.com/skruxmusic\nhttps://twitter.com/Skrux\n\nSheepy on Spotify\nhttp://bit.ly/MrSuicideSheepSpotify",
    "duration": 274,
    "genre": "Dubstep",
    "title": "Tides",
    "username": "MrSuicideSheep",
    "artist": "Crywolf",
    "remixArtist": null,
    "labelname": "",
    "id": 46707185,
    "isRemix": false,
    "search_stage": 1,
    "url": "https://soundcloud.com/mrsuicidesheep/crywolf-skrux-tides"
  },
  "Results": [
    {
      "description": "",
      "duration": 367,
      "genre": "",
      "title": "Heart Attack",
      "username": "Various Artists",
      "artist": "Various Artists",
      "remixArtist": null,
      "labelname": "",
      "id": 69113322,
      "isRemix": false,
      "search_stage": 0,
      "url": "https://www.deezer.com/track/69113322"
    }
  ]
}