{
  "Searching": {
    "description": "Listen on spotify: https://www.hive.co/l/spotifyezylima\n\nDownload/Stream: https://EzyLima.lnk.to/MDMer\n\nSign Up for my Newsletter to receive my free Mixtape Series & other news about me:\nhttps://www.hive.co/l/ezylimanews\n\nFollow EZY Lima:\nhttps://www.facebook.com/EZYLimaofficial\nhttps://www.youtube.com/user/ezylima\nhttps://twitter.com/EZYLimaofficial\nhttps://instagram.com/ezy_lima/\nhttps://soundcloud.com/ezy-lima\n\nFollow Tayler Buono\nhttp://www.TaylerBuono.com\nhttps://www.instagram.com/TaylerBuono/\nhttps://www.facebook.com/taylerbuonomusic/\nhttps://twitter.com/taylerbuono\n",
    "duration": 245,
    "genre": "EZY Lima ",
    "title": "Sorry -",
    "username": "EZY Lima",
    "artist": "Justin Bieber",
    "remixArtist": null,
    "labelname": "",
    "id": 181253306,
    "isRemix": true,
    "search_stage": 1,
    "url": "https://soundcloud.com/ezy-lima/justin-bieber-sorry-cover-by-tayler-buono-ezy-lima-remix"
  },
  "Results": [
    {
      "description": "",
      "duration": 189,
      "genre": "",
      "title": "Love Me",
      "username": "The Karaoke Channel",
      "artist": "The Karaoke Channel",
      "remixArtist": null,
      "labelname": "",
      "id": 67541143,
      "isRemix": false,
      "search_stage": 0,
      "url": "https://www.deezer.com/track/67541143"
    }
  ]
}