{
  "Searching": {
    "description": "Hey everybody! Here is a song I did with my good friend @directmusic We both had a ton of fun making this tune. Hope you all enjoy it!!\n\nhttps://twitter.com/iamfindinghope\nhttps://www.facebook.com/findinghopemusic/\n\nSteam on Spotify, iTunes and more!\nhttps://direct.lnk.to/FallingIntoPlace",
    "duration": 254,
    "genre": "Ambient",
    "title": "Falling Into Place",
    "username": "Finding Hope",
    "artist": "Direct  Finding Hope",
    "remixArtist": null,
    "labelname": "",
    "id": 181253306,
    "isRemix": false,
    "search_stage": 3,
    "url": "https://soundcloud.com/findinghopemusic/falling-into-place"
  },
  "Results": []
}