{
  "Searching": {
    "description": "Brand new remix for Zara Larsson!\n\nCheck out my brand new record ''Icarus'' and make sure to follow my playlist www.r3habplaylist.com",
    "duration": 158,
    "genre": "Dance & EDM",
    "title": "Aint My Fault",
    "username": "R3HAB",
    "artist": "Zara Larsson",
    "remixArtist": "R3hab",
    "labelname": "",
    "id": 181253306,
    "isRemix": true,
    "search_stage": 3,
    "url": "https://soundcloud.com/r3hab/zara-larsson-aint-my-fault-r3hab-remix"
  },
  "Results": [
    {
      "description": "",
      "duration": 212,
      "genre": "",
      "title": "Symphony",
      "username": "Clean Bandit",
      "artist": "Clean Bandit",
      "remixArtist": null,
      "labelname": "",
      "id": 144393668,
      "isRemix": false,
      "search_stage": 0,
      "url": "https://www.deezer.com/track/144393668"
    },
    {
      "description": "",
      "duration": 201,
      "genre": "",
      "title": "Lush Life",
      "username": "Zara Larsson",
      "artist": "Zara Larsson",
      "remixArtist": null,
      "labelname": "",
      "id": 144389048,
      "isRemix": false,
      "search_stage": 0,
      "url": "https://www.deezer.com/track/144389048"
    },
    {
      "description": "",
      "duration": 213,
      "genre": "",
      "title": "Uncover",
      "username": "Zara Larsson",
      "artist": "Zara Larsson",
      "remixArtist": null,
      "labelname": "",
      "id": 93194632,
      "isRemix": false,
      "search_stage": 0,
      "url": "https://www.deezer.com/track/93194632"
    },
    {
      "description": "",
      "duration": 190,
      "genre": "",
      "title": "Ruin My Life",
      "username": "Zara Larsson",
      "artist": "Zara Larsson",
      "remixArtist": null,
      "labelname": "",
      "id": 589312552,
      "isRemix": false,
      "search_stage": 0,
      "url": "https://www.deezer.com/track/589312552"
    },
    {
      "description": "",
      "duration": 173,
      "genre": "",
      "title": "Invisible",
      "username": "Zara Larsson",
      "artist": "Zara Larsson",
      "remixArtist": null,
      "labelname": "",
      "id": 798346952,
      "isRemix": false,
      "search_stage": 0,
      "url": "https://www.deezer.com/track/798346952"
    },
    {
      "description": "",
      "duration": 228,
      "genre": "",
      "title": "All the Time",
      "username": "Zara Larsson",
      "artist": "Zara Larsson",
      "remixArtist": null,
      "labelname": "",
      "id": 697727622,
      "isRemix": false,
      "search_stage": 0,
      "url": "https://www.deezer.com/track/697727622"
    },
    {
      "description": "",
      "duration": 190,
      "genre": "",
      "title": "Ruin My Life",
      "username": "Zara Larsson",
      "artist": "Zara Larsson",
      "remixArtist": null,
      "labelname": "",
      "id": 566589132,
      "isRemix": false,
      "search_stage": 0,
      "url": "https://www.deezer.com/track/566589132"
    },
    {
      "description": "",
      "duration": 220,
      "genre": "",
      "title": "Ain't My Fault",
      "username": "Zara Larsson",
      "artist": "Zara Larsson",
      "remixArtist": null,
      "labelname": "",
      "id": 131340458,
      "isRemix": false,
      "search_stage": 0,
      "url": "https://www.deezer.com/track/131340458"
    },
    {
      "description": "",
      "duration": 208,
      "genre": "",
      "title": "Don't Worry Bout Me",
      "username": "Zara Larsson",
      "artist": "Zara Larsson",
      "remixArtist": null,
      "labelname": "",
      "id": 655315852,
      "isRemix": false,
      "search_stage": 0,
      "url": "https://www.deezer.com/track/655315852"
    },
    {
      "description": "",
      "duration": 179,
      "genre": "",
      "title": "WOW",
      "username": "Zara Larsson",
      "artist": "Zara Larsson",
      "remixArtist": null,
      "labelname": "",
      "id": 659373382,
      "isRemix": false,
      "search_stage": 0,
      "url": "https://www.deezer.com/track/659373382"
    },
    {
      "description": "",
      "duration": 226,
      "genre": "",
      "title": "I Would Like",
      "username": "Zara Larsson",
      "artist": "Zara Larsson",
      "remixArtist": null,
      "labelname": "",
      "id": 144389050,
      "isRemix": false,
      "search_stage": 0,
      "url": "https://www.deezer.com/track/144389050"
    },
    {
      "description": "",
      "duration": 180,
      "genre": "",
      "title": "I Can't Fall in Love Without You",
      "username": "Zara Larsson",
      "artist": "Zara Larsson",
      "remixArtist": null,
      "labelname": "",
      "id": 144389072,
      "isRemix": false,
      "search_stage": 0,
      "url": "https://www.deezer.com/track/144389072"
    },
    {
      "description": "",
      "duration": 196,
      "genre": "",
      "title": "Girls Like",
      "username": "Tinie Tempah",
      "artist": "Tinie Tempah",
      "remixArtist": null,
      "labelname": "",
      "id": 119967906,
      "isRemix": false,
      "search_stage": 0,
      "url": "https://www.deezer.com/track/119967906"
    },
    {
      "description": "",
      "duration": 213,
      "genre": "",
      "title": "Never Forget You",
      "username": "Zara Larsson",
      "artist": "Zara Larsson",
      "remixArtist": null,
      "labelname": "",
      "id": 144389058,
      "isRemix": false,
      "search_stage": 0,
      "url": "https://www.deezer.com/track/144389058"
    },
    {
      "description": "",
      "duration": 205,
      "genre": "",
      "title": "A Brand New Day",
      "username": "BTS",
      "artist": "BTS",
      "remixArtist": null,
      "labelname": "",
      "id": 694166792,
      "isRemix": false,
      "search_stage": 0,
      "url": "https://www.deezer.com/track/694166792"
    },
    {
      "description": "",
      "duration": 224,
      "genre": "",
      "title": "Ain't My Fault",
      "username": "Zara Larsson",
      "artist": "Zara Larsson",
      "remixArtist": null,
      "labelname": "",
      "id": 144389066,
      "isRemix": false,
      "search_stage": 0,
      "url": "https://www.deezer.com/track/144389066"
    },
    {
      "description": "",
      "duration": 205,
      "genre": "",
      "title": "A Brand New Day",
      "username": "BTS",
      "artist": "BTS",
      "remixArtist": null,
      "labelname": "",
      "id": 700028732,
      "isRemix": false,
      "search_stage": 0,
      "url": "https://www.deezer.com/track/700028732"
    },
    {
      "description": "",
      "duration": 216,
      "genre": "",
      "title": "Symphony",
      "username": "Clean Bandit",
      "artist": "Clean Bandit",
      "remixArtist": null,
      "labelname": "",
      "id": 344854081,
      "isRemix": false,
      "search_stage": 0,
      "url": "https://www.deezer.com/track/344854081"
    },
    {
      "description": "",
      "duration": 332,
      "genre": "",
      "title": "She's Not Me, Pt. 1  2",
      "username": "Zara Larsson",
      "artist": "Zara Larsson",
      "remixArtist": null,
      "labelname": "",
      "id": 93194636,
      "isRemix": false,
      "search_stage": 0,
      "url": "https://www.deezer.com/track/93194636"
    },
    {
      "description": "",
      "duration": 222,
      "genre": "",
      "title": "Only You",
      "username": "Zara Larsson",
      "artist": "Zara Larsson",
      "remixArtist": null,
      "labelname": "",
      "id": 144389056,
      "isRemix": false,
      "search_stage": 0,
      "url": "https://www.deezer.com/track/144389056"
    },
    {
      "description": "",
      "duration": 202,
      "genre": "",
      "title": "Lush Life",
      "username": "Zara Larsson",
      "artist": "Zara Larsson",
      "remixArtist": null,
      "labelname": "",
      "id": 122109068,
      "isRemix": false,
      "search_stage": 0,
      "url": "https://www.deezer.com/track/122109068"
    },
    {
      "description": "",
      "duration": 254,
      "genre": "",
      "title": "Carry You Home",
      "username": "Zara Larsson",
      "artist": "Zara Larsson",
      "remixArtist": null,
      "labelname": "",
      "id": 93194634,
      "isRemix": false,
      "search_stage": 0,
      "url": "https://www.deezer.com/track/93194634"
    },
    {
      "description": "",
      "duration": 199,
      "genre": "",
      "title": "Don't Let Me Be Yours",
      "username": "Zara Larsson",
      "artist": "Zara Larsson",
      "remixArtist": null,
      "labelname": "",
      "id": 144389062,
      "isRemix": false,
      "search_stage": 0,
      "url": "https://www.deezer.com/track/144389062"
    },
    {
      "description": "",
      "duration": 190,
      "genre": "",
      "title": "Ruin My Life",
      "username": "Zara Larsson",
      "artist": "Zara Larsson",
      "remixArtist": null,
      "labelname": "",
      "id": 566564032,
      "isRemix": false,
      "search_stage": 0,
      "url": "https://www.deezer.com/track/566564032"
    },
    {
      "description": "",
      "duration": 179,
      "genre": "",
      "title": "WOW",
      "username": "Zara Larsson",
      "artist": "Zara Larsson",
      "remixArtist": null,
      "labelname": "",
      "id": 659373372,
      "isRemix": false,
      "search_stage": 0,
      "url": "https://www.deezer.com/track/659373372"
    }
  ]
}