{
  "Searching": {
    "description": "🎧 Support on all platforms: https://monster.cat/run\n\n▼ Follow Monstercat\nSpotify: https://monster.cat/2biZbkd\nApple: https://apple.co/2xiKWTO\nFacebook: https://facebook.com/monstercat\nTwitter: https://twitter.com/monstercat\nInstagram: https://instagram.com/monstercat\n\n▼ Follow ShockOne\nFacebook: https://facebook.com/shockonemusic\nTwitter: https://twitter.com/therealshockone\nInstagram: https://instagram.com/therealshockone\nSoundCloud: https://soundcloud.com/shockone\n\n▼ Follow The Bloody Beetroots\nFacebook: https://facebook.com/thebloodybeetroots\nTwitter: https://twitter.com/BloodyBeetroots\nInstagram: https://instagram.com/thebloodybeetrootsofficial\nSoundCloud: https://soundcloud.com/thebloodybeetroots\n\nGenre: #ElectroHouse\n\n▼ Want some new Merchandise?\nhttps://monster.cat/MonstercatShop\n\n▼ Download with Gold!\nhttps://monster.cat/goldyt\n\n▼ Submit to Monstercat!\nhttp://monster.cat/demo-submissions",
    "duration": 302,
    "genre": "Electro House",
    "title": "Run",
    "username": "Monstercat",
    "artist": "ShockOne",
    "remixArtist": null,
    "labelname": "Monstercat",
    "id": 703645755,
    "isRemix": false,
    "search_stage": 3,
    "url": "https://soundcloud.com/monstercat/shockone-run-feat-the-bloody-beetroots"
  },
  "Reported": {
    "description": "",
    "duration": 301,
    "genre": "",
    "title": "Run",
    "username": "SHOCKONE",
    "artist": "SHOCKONE",
    "remixArtist": null,
    "labelname": "",
    "id": 703789362,
    "isRemix": false,
    "search_stage": 0,
    "url": "https://www.deezer.com/track/703789362"
  },
  "Results": [
    {
      "description": "",
      "duration": 273,
      "genre": "",
      "title": "Pray For Me",
      "username": "SHOCKONE",
      "artist": "SHOCKONE",
      "remixArtist": null,
      "labelname": "",
      "id": 720905232,
      "isRemix": false,
      "search_stage": 0,
      "url": "https://www.deezer.com/track/720905232"
    },
    {
      "description": "",
      "duration": 323,
      "genre": "",
      "title": "Til Dawn",
      "username": "SHOCKONE",
      "artist": "SHOCKONE",
      "remixArtist": null,
      "labelname": "",
      "id": 720589032,
      "isRemix": false,
      "search_stage": 0,
      "url": "https://www.deezer.com/track/720589032"
    },
    {
      "description": "",
      "duration": 323,
      "genre": "",
      "title": "Til Dawn",
      "username": "SHOCKONE",
      "artist": "SHOCKONE",
      "remixArtist": null,
      "labelname": "",
      "id": 712256132,
      "isRemix": false,
      "search_stage": 0,
      "url": "https://www.deezer.com/track/712256132"
    },
    {
      "description": "",
      "duration": 212,
      "genre": "",
      "title": "Lost It",
      "username": "SHOCKONE",
      "artist": "SHOCKONE",
      "remixArtist": null,
      "labelname": "",
      "id": 720905182,
      "isRemix": false,
      "search_stage": 0,
      "url": "https://www.deezer.com/track/720905182"
    },
    {
      "description": "",
      "duration": 301,
      "genre": "",
      "title": "Run",
      "username": "SHOCKONE",
      "artist": "SHOCKONE",
      "remixArtist": null,
      "labelname": "",
      "id": 703789362,
      "isRemix": false,
      "search_stage": 0,
      "url": "https://www.deezer.com/track/703789362"
    },
    {
      "description": "",
      "duration": 124,
      "genre": "",
      "title": "Willow's Theme",
      "username": "SHOCKONE",
      "artist": "SHOCKONE",
      "remixArtist": null,
      "labelname": "",
      "id": 720905252,
      "isRemix": false,
      "search_stage": 0,
      "url": "https://www.deezer.com/track/720905252"
    },
    {
      "description": "",
      "duration": 414,
      "genre": "",
      "title": "Light Cycles",
      "username": "SHOCKONE",
      "artist": "SHOCKONE",
      "remixArtist": null,
      "labelname": "",
      "id": 65760866,
      "isRemix": false,
      "search_stage": 0,
      "url": "https://www.deezer.com/track/65760866"
    },
    {
      "description": "",
      "duration": 322,
      "genre": "",
      "title": "Chaos Theory",
      "username": "SHOCKONE",
      "artist": "SHOCKONE",
      "remixArtist": null,
      "labelname": "",
      "id": 61102538,
      "isRemix": false,
      "search_stage": 0,
      "url": "https://www.deezer.com/track/61102538"
    },
    {
      "description": "",
      "duration": 433,
      "genre": "",
      "title": "Home",
      "username": "SHOCKONE",
      "artist": "SHOCKONE",
      "remixArtist": null,
      "labelname": "",
      "id": 65760856,
      "isRemix": false,
      "search_stage": 0,
      "url": "https://www.deezer.com/track/65760856"
    },
    {
      "description": "",
      "duration": 386,
      "genre": "",
      "title": "Crucify Me Part 1",
      "username": "SHOCKONE",
      "artist": "SHOCKONE",
      "remixArtist": null,
      "labelname": "",
      "id": 60904982,
      "isRemix": false,
      "search_stage": 0,
      "url": "https://www.deezer.com/track/60904982"
    },
    {
      "description": "",
      "duration": 263,
      "genre": "",
      "title": "Lazerbeam",
      "username": "SHOCKONE",
      "artist": "SHOCKONE",
      "remixArtist": null,
      "labelname": "",
      "id": 66618410,
      "isRemix": false,
      "search_stage": 0,
      "url": "https://www.deezer.com/track/66618410"
    },
    {
      "description": "",
      "duration": 378,
      "genre": "",
      "title": "Polygon",
      "username": "SHOCKONE",
      "artist": "SHOCKONE",
      "remixArtist": null,
      "labelname": "",
      "id": 90403575,
      "isRemix": false,
      "search_stage": 0,
      "url": "https://www.deezer.com/track/90403575"
    },
    {
      "description": "",
      "duration": 248,
      "genre": "",
      "title": "Body Movin'",
      "username": "Cyantific",
      "artist": "Cyantific",
      "remixArtist": null,
      "labelname": "",
      "id": 482216612,
      "isRemix": false,
      "search_stage": 0,
      "url": "https://www.deezer.com/track/482216612"
    },
    {
      "description": "",
      "duration": 301,
      "genre": "",
      "title": "Run",
      "username": "SHOCKONE",
      "artist": "SHOCKONE",
      "remixArtist": null,
      "labelname": "",
      "id": 720588752,
      "isRemix": false,
      "search_stage": 0,
      "url": "https://www.deezer.com/track/720588752"
    },
    {
      "description": "",
      "duration": 227,
      "genre": "",
      "title": "A Dark Machine",
      "username": "SHOCKONE",
      "artist": "SHOCKONE",
      "remixArtist": null,
      "labelname": "",
      "id": 720905162,
      "isRemix": false,
      "search_stage": 0,
      "url": "https://www.deezer.com/track/720905162"
    },
    {
      "description": "",
      "duration": 326,
      "genre": "",
      "title": "Crucify Me",
      "username": "SHOCKONE",
      "artist": "SHOCKONE",
      "remixArtist": null,
      "labelname": "",
      "id": 65760859,
      "isRemix": false,
      "search_stage": 0,
      "url": "https://www.deezer.com/track/65760859"
    },
    {
      "description": "",
      "duration": 239,
      "genre": "",
      "title": "Underloved",
      "username": "SHOCKONE",
      "artist": "SHOCKONE",
      "remixArtist": null,
      "labelname": "",
      "id": 720905212,
      "isRemix": false,
      "search_stage": 0,
      "url": "https://www.deezer.com/track/720905212"
    },
    {
      "description": "",
      "duration": 231,
      "genre": "",
      "title": "Bleed Black",
      "username": "SHOCKONE",
      "artist": "SHOCKONE",
      "remixArtist": null,
      "labelname": "",
      "id": 720905172,
      "isRemix": false,
      "search_stage": 0,
      "url": "https://www.deezer.com/track/720905172"
    },
    {
      "description": "",
      "duration": 430,
      "genre": "",
      "title": "Home",
      "username": "SHOCKONE",
      "artist": "SHOCKONE",
      "remixArtist": null,
      "labelname": "",
      "id": 81551724,
      "isRemix": false,
      "search_stage": 0,
      "url": "https://www.deezer.com/track/81551724"
    },
    {
      "description": "",
      "duration": 331,
      "genre": "",
      "title": "Universes",
      "username": "SHOCKONE",
      "artist": "SHOCKONE",
      "remixArtist": null,
      "labelname": "",
      "id": 65760860,
      "isRemix": false,
      "search_stage": 0,
      "url": "https://www.deezer.com/track/65760860"
    },
    {
      "description": "",
      "duration": 328,
      "genre": "",
      "title": "The One",
      "username": "Brookes Brothers",
      "artist": "Brookes Brothers",
      "remixArtist": null,
      "labelname": "",
      "id": 391107482,
      "isRemix": false,
      "search_stage": 0,
      "url": "https://www.deezer.com/track/391107482"
    },
    {
      "description": "",
      "duration": 301,
      "genre": "",
      "title": "Run",
      "username": "SHOCKONE",
      "artist": "SHOCKONE",
      "remixArtist": null,
      "labelname": "",
      "id": 720905142,
      "isRemix": false,
      "search_stage": 0,
      "url": "https://www.deezer.com/track/720905142"
    },
    {
      "description": "",
      "duration": 242,
      "genre": "",
      "title": "Showdown",
      "username": "Virtual Riot",
      "artist": "Virtual Riot",
      "remixArtist": null,
      "labelname": "",
      "id": 438630002,
      "isRemix": false,
      "search_stage": 0,
      "url": "https://www.deezer.com/track/438630002"
    },
    {
      "description": "",
      "duration": 221,
      "genre": "",
      "title": "Klaxon",
      "username": "SHOCKONE",
      "artist": "SHOCKONE",
      "remixArtist": null,
      "labelname": "",
      "id": 720905202,
      "isRemix": false,
      "search_stage": 0,
      "url": "https://www.deezer.com/track/720905202"
    },
    {
      "description": "",
      "duration": 311,
      "genre": "",
      "title": "Chaos Theory",
      "username": "SHOCKONE",
      "artist": "SHOCKONE",
      "remixArtist": null,
      "labelname": "",
      "id": 65760854,
      "isRemix": false,
      "search_stage": 0,
      "url": "https://www.deezer.com/track/65760854"
    }
  ]
}