{
  "Searching": {
    "description": "🎧 Support on all platforms: https://Monstercat.lnk.to/Questions\n\n▼ Follow Monstercat\nSpotify: http://monster.cat/2biZbkd\nApple Music: http://apple.co/2xiKWTO\nFacebook: http://facebook.com/Monstercat\nTwitter: http://twitter.com/Monstercat\nInstagram: http://instagram.com/monstercat\nSnapchat: https://www.snapchat.com/add/monstercat\nSoundCloud: http://soundcloud.com/Monstercat\n\n💥 Follow Tristam\nFacebook: https://www.facebook.com/Theofficialtristam\nTwitter: http://twitter.com/TristamOfficial\nSoundcloud: https://soundcloud.com/Tristam\nYoutube: http://youtube.com/TheOfficialTristam\n\nGenre: #Electronic\n\n▼ Want some new Merchandise?\nhttp://monster.cat/MonstercatShop",
    "duration": 250,
    "genre": "Electronic",
    "title": "Questions",
    "username": "Monstercat",
    "artist": "Tristam",
    "remixArtist": null,
    "labelname": "Monstercat",
    "id": 429178226,
    "isRemix": false,
    "search_stage": 1,
    "url": "https://soundcloud.com/monstercat/tristam-questions"
  },
  "Reported": {
    "description": "",
    "duration": 250,
    "genre": "",
    "title": "Questions",
    "username": "Various Artists",
    "artist": "Various Artists",
    "remixArtist": null,
    "labelname": "",
    "id": 518852842,
    "isRemix": false,
    "search_stage": 0,
    "url": "https://www.deezer.com/track/518852842"
  },
  "Results": [
    {
      "description": "",
      "duration": 247,
      "genre": "",
      "title": "Before We Fade",
      "username": "Various Artists",
      "artist": "Various Artists",
      "remixArtist": null,
      "labelname": "",
      "id": 128642585,
      "isRemix": false,
      "search_stage": 0,
      "url": "https://www.deezer.com/track/128642585"
    },
    {
      "description": "",
      "duration": 250,
      "genre": "",
      "title": "Questions",
      "username": "Various Artists",
      "artist": "Various Artists",
      "remixArtist": null,
      "labelname": "",
      "id": 518852842,
      "isRemix": false,
      "search_stage": 0,
      "url": "https://www.deezer.com/track/518852842"
    },
    {
      "description": "",
      "duration": 316,
      "genre": "",
      "title": "Devotion",
      "username": "Various Artists",
      "artist": "Various Artists",
      "remixArtist": null,
      "labelname": "",
      "id": 137904685,
      "isRemix": false,
      "search_stage": 0,
      "url": "https://www.deezer.com/track/137904685"
    },
    {
      "description": "",
      "duration": 270,
      "genre": "",
      "title": "Far Away",
      "username": "Various Artists",
      "artist": "Various Artists",
      "remixArtist": null,
      "labelname": "",
      "id": 117402826,
      "isRemix": false,
      "search_stage": 0,
      "url": "https://www.deezer.com/track/117402826"
    },
    {
      "description": "",
      "duration": 285,
      "genre": "",
      "title": "Bone Dry",
      "username": "Various Artists",
      "artist": "Various Artists",
      "remixArtist": null,
      "labelname": "",
      "id": 440766452,
      "isRemix": false,
      "search_stage": 0,
      "url": "https://www.deezer.com/track/440766452"
    },
    {
      "description": "",
      "duration": 309,
      "genre": "",
      "title": "Crave",
      "username": "Various Artists",
      "artist": "Various Artists",
      "remixArtist": null,
      "labelname": "",
      "id": 117402836,
      "isRemix": false,
      "search_stage": 0,
      "url": "https://www.deezer.com/track/117402836"
    },
    {
      "description": "",
      "duration": 215,
      "genre": "",
      "title": "Looking back",
      "username": "Various Artists",
      "artist": "Various Artists",
      "remixArtist": null,
      "labelname": "",
      "id": 768086502,
      "isRemix": false,
      "search_stage": 0,
      "url": "https://www.deezer.com/track/768086502"
    },
    {
      "description": "",
      "duration": 240,
      "genre": "",
      "title": "Candlelight Dreams",
      "username": "Various Artists",
      "artist": "Various Artists",
      "remixArtist": null,
      "labelname": "",
      "id": 618335042,
      "isRemix": false,
      "search_stage": 0,
      "url": "https://www.deezer.com/track/618335042"
    },
    {
      "description": "",
      "duration": 218,
      "genre": "",
      "title": "Prettiest",
      "username": "Various Artists",
      "artist": "Various Artists",
      "remixArtist": null,
      "labelname": "",
      "id": 664511562,
      "isRemix": false,
      "search_stage": 0,
      "url": "https://www.deezer.com/track/664511562"
    },
    {
      "description": "",
      "duration": 249,
      "genre": "",
      "title": "Tonight, Love Under the Moon",
      "username": "Various Artists",
      "artist": "Various Artists",
      "remixArtist": null,
      "labelname": "",
      "id": 463450972,
      "isRemix": false,
      "search_stage": 0,
      "url": "https://www.deezer.com/track/463450972"
    },
    {
      "description": "",
      "duration": 248,
      "genre": "",
      "title": "No Worries",
      "username": "Various Artists",
      "artist": "Various Artists",
      "remixArtist": null,
      "labelname": "",
      "id": 618335002,
      "isRemix": false,
      "search_stage": 0,
      "url": "https://www.deezer.com/track/618335002"
    }
  ]
}