{
  "Searching": {
    "description": "•Proximity - Your favorite music you haven't heard yet.\n» Facebook: http://bit.ly/FBProximity\n» Twitter: http://bit.ly/ProximityTwitter\n\nSuch an amazing track. Steerner and Kavela (new artist who I haven't heard of yet but impresses me) killed with with Matthew Steeper's beautiful vocals. Hope you all enjoy! :)\n\n•Steerner:\nhttps://soundcloud.com/steernermusic\nhttps://www.facebook.com/SteernerOffi...\nhttps://twitter.com/Steerner\n\n•Kavela:\nwww.facebook.com/kavelamusic\nhttps://soundcloud.com/kavelamusic\n\n•Matthew Steeper:\nhttps://facebook.com/matthewsteeperof...\n\nPicture by: Martin K.\n\nIf you'd like to submit a picture, you can send it here:\nhttp://pandoric.com/contact\n\nUse the new template if you would like to submit a picture! :)\nhttp://goo.gl/yoEGNg",
    "duration": 213,
    "genre": "Progressive House",
    "title": "Horizon",
    "username": "Proximity",
    "artist": "Steerner",
    "remixArtist": null,
    "labelname": "",
    "id": 85497378,
    "isRemix": false,
    "search_stage": 3,
    "url": "https://soundcloud.com/proximity/steerner-kavela-ft-matthew-steeper-horizon-proximity-release"
  },
  "Reported": {
    "description": "",
    "duration": 213,
    "genre": "",
    "title": "Zyzz",
    "username": "Steerner  Tjernberg",
    "artist": "Steerner & Tjernberg",
    "remixArtist": null,
    "labelname": "",
    "id": 86157815,
    "isRemix": false,
    "search_stage": 0,
    "url": "https://www.deezer.com/track/86157815"
  },
  "Results": [
    {
      "description": "",
      "duration": 168,
      "genre": "",
      "title": "I Wouldn't Lie",
      "username": "Steerner",
      "artist": "Steerner",
      "remixArtist": null,
      "labelname": "",
      "id": 502745282,
      "isRemix": false,
      "search_stage": 0,
      "url": "https://www.deezer.com/track/502745282"
    },
    {
      "description": "",
      "duration": 325,
      "genre": "",
      "title": "Friends",
      "username": "Steerner",
      "artist": "Steerner",
      "remixArtist": null,
      "labelname": "",
      "id": 60974869,
      "isRemix": false,
      "search_stage": 0,
      "url": "https://www.deezer.com/track/60974869"
    },
    {
      "description": "",
      "duration": 201,
      "genre": "",
      "title": "Off My Mind",
      "username": "Steerner",
      "artist": "Steerner",
      "remixArtist": null,
      "labelname": "",
      "id": 568139782,
      "isRemix": false,
      "search_stage": 0,
      "url": "https://www.deezer.com/track/568139782"
    },
    {
      "description": "",
      "duration": 188,
      "genre": "",
      "title": "Nowhere",
      "username": "Steerner",
      "artist": "Steerner",
      "remixArtist": null,
      "labelname": "",
      "id": 446737482,
      "isRemix": false,
      "search_stage": 0,
      "url": "https://www.deezer.com/track/446737482"
    },
    {
      "description": "",
      "duration": 213,
      "genre": "",
      "title": "Zyzz",
      "username": "Steerner  Tjernberg",
      "artist": "Steerner & Tjernberg",
      "remixArtist": null,
      "labelname": "",
      "id": 86157815,
      "isRemix": false,
      "search_stage": 0,
      "url": "https://www.deezer.com/track/86157815"
    },
    {
      "description": "",
      "duration": 201,
      "genre": "",
      "title": "Broken Hearted",
      "username": "Liamoo",
      "artist": "Liamoo",
      "remixArtist": null,
      "labelname": "",
      "id": 678705302,
      "isRemix": false,
      "search_stage": 0,
      "url": "https://www.deezer.com/track/678705302"
    },
    {
      "description": "",
      "duration": 226,
      "genre": "",
      "title": "YOU",
      "username": "Steerner",
      "artist": "Steerner",
      "remixArtist": null,
      "labelname": "",
      "id": 729597042,
      "isRemix": false,
      "search_stage": 0,
      "url": "https://www.deezer.com/track/729597042"
    },
    {
      "description": "",
      "duration": 236,
      "genre": "",
      "title": "Sky",
      "username": "Steerner",
      "artist": "Steerner",
      "remixArtist": null,
      "labelname": "",
      "id": 90213931,
      "isRemix": false,
      "search_stage": 0,
      "url": "https://www.deezer.com/track/90213931"
    },
    {
      "description": "",
      "duration": 196,
      "genre": "",
      "title": "Blue",
      "username": "Steerner",
      "artist": "Steerner",
      "remixArtist": null,
      "labelname": "",
      "id": 103571212,
      "isRemix": false,
      "search_stage": 0,
      "url": "https://www.deezer.com/track/103571212"
    },
    {
      "description": "",
      "duration": 201,
      "genre": "",
      "title": "Crystals",
      "username": "Steerner",
      "artist": "Steerner",
      "remixArtist": null,
      "labelname": "",
      "id": 103571210,
      "isRemix": false,
      "search_stage": 0,
      "url": "https://www.deezer.com/track/103571210"
    },
    {
      "description": "",
      "duration": 210,
      "genre": "",
      "title": "Sun",
      "username": "Steerner",
      "artist": "Steerner",
      "remixArtist": null,
      "labelname": "",
      "id": 103571208,
      "isRemix": false,
      "search_stage": 0,
      "url": "https://www.deezer.com/track/103571208"
    },
    {
      "description": "",
      "duration": 172,
      "genre": "",
      "title": "Warfare",
      "username": "Steerner",
      "artist": "Steerner",
      "remixArtist": null,
      "labelname": "",
      "id": 114066534,
      "isRemix": false,
      "search_stage": 0,
      "url": "https://www.deezer.com/track/114066534"
    },
    {
      "description": "",
      "duration": 229,
      "genre": "",
      "title": "Alive",
      "username": "Steerner  Tobu",
      "artist": "Steerner & Tobu",
      "remixArtist": null,
      "labelname": "",
      "id": 134904028,
      "isRemix": false,
      "search_stage": 0,
      "url": "https://www.deezer.com/track/134904028"
    },
    {
      "description": "",
      "duration": 195,
      "genre": "",
      "title": "Sparks",
      "username": "Steerner",
      "artist": "Steerner",
      "remixArtist": null,
      "labelname": "",
      "id": 94505482,
      "isRemix": false,
      "search_stage": 0,
      "url": "https://www.deezer.com/track/94505482"
    },
    {
      "description": "",
      "duration": 221,
      "genre": "",
      "title": "Piano Anthem!",
      "username": "Steerner",
      "artist": "Steerner",
      "remixArtist": null,
      "labelname": "",
      "id": 14270907,
      "isRemix": false,
      "search_stage": 0,
      "url": "https://www.deezer.com/track/14270907"
    },
    {
      "description": "",
      "duration": 263,
      "genre": "",
      "title": "Young Love",
      "username": "Steerner",
      "artist": "Steerner",
      "remixArtist": null,
      "labelname": "",
      "id": 62069583,
      "isRemix": false,
      "search_stage": 0,
      "url": "https://www.deezer.com/track/62069583"
    },
    {
      "description": "",
      "duration": 266,
      "genre": "",
      "title": "Friends",
      "username": "Steerner",
      "artist": "Steerner",
      "remixArtist": null,
      "labelname": "",
      "id": 62069584,
      "isRemix": false,
      "search_stage": 0,
      "url": "https://www.deezer.com/track/62069584"
    },
    {
      "description": "",
      "duration": 172,
      "genre": "",
      "title": "Polar",
      "username": "Steerner",
      "artist": "Steerner",
      "remixArtist": null,
      "labelname": "",
      "id": 124847268,
      "isRemix": false,
      "search_stage": 0,
      "url": "https://www.deezer.com/track/124847268"
    },
    {
      "description": "",
      "duration": 189,
      "genre": "",
      "title": "Burning Daylight",
      "username": "Steerner x Wahlstedt",
      "artist": "Steerner x Wahlstedt",
      "remixArtist": null,
      "labelname": "",
      "id": 361553981,
      "isRemix": false,
      "search_stage": 0,
      "url": "https://www.deezer.com/track/361553981"
    },
    {
      "description": "",
      "duration": 251,
      "genre": "",
      "title": "Bright Lights",
      "username": "Syn Cole",
      "artist": "Syn Cole",
      "remixArtist": null,
      "labelname": "",
      "id": 84882593,
      "isRemix": false,
      "search_stage": 0,
      "url": "https://www.deezer.com/track/84882593"
    },
    {
      "description": "",
      "duration": 224,
      "genre": "",
      "title": "Waves",
      "username": "Steerner",
      "artist": "Steerner",
      "remixArtist": null,
      "labelname": "",
      "id": 68118610,
      "isRemix": false,
      "search_stage": 0,
      "url": "https://www.deezer.com/track/68118610"
    },
    {
      "description": "",
      "duration": 253,
      "genre": "",
      "title": "Capture",
      "username": "Steerner  Tjernberg",
      "artist": "Steerner & Tjernberg",
      "remixArtist": null,
      "labelname": "",
      "id": 16145516,
      "isRemix": false,
      "search_stage": 0,
      "url": "https://www.deezer.com/track/16145516"
    },
    {
      "description": "",
      "duration": 230,
      "genre": "",
      "title": "Fight Forever",
      "username": "Steerner",
      "artist": "Steerner",
      "remixArtist": null,
      "labelname": "",
      "id": 103054224,
      "isRemix": false,
      "search_stage": 0,
      "url": "https://www.deezer.com/track/103054224"
    },
    {
      "description": "",
      "duration": 204,
      "genre": "",
      "title": "Calling",
      "username": "Tobu",
      "artist": "Tobu",
      "remixArtist": "Steerner",
      "labelname": "",
      "id": 469656932,
      "isRemix": true,
      "search_stage": 0,
      "url": "https://www.deezer.com/track/469656932"
    },
    {
      "description": "",
      "duration": 315,
      "genre": "",
      "title": "Tomorrow",
      "username": "Steerner  Widing",
      "artist": "Steerner & Widing",
      "remixArtist": null,
      "labelname": "",
      "id": 62484176,
      "isRemix": false,
      "search_stage": 0,
      "url": "https://www.deezer.com/track/62484176"
    }
  ]
}